autobuffer/__init__.py
autobuffer/autobuffer.py
autobuffer-0.0.9.dist-info/LICENSE
autobuffer-0.0.9.dist-info/METADATA
autobuffer-0.0.9.dist-info/WHEEL
autobuffer-0.0.9.dist-info/top_level.txt
autobuffer-0.0.9.dist-info/RECORD
