Metadata-Version: 2.1
Name: autobuffer
Version: 0.0.9
Summary: A simple and fast automatic double buffer class
Author-email: João Dias Carrilho <author@example.com>
Project-URL: Homepage, https://github.com/jadc197/autobuffer
Project-URL: Bug Tracker, https://github.com/jadc197/autobuffer/issues
Classifier: Programming Language :: Python :: 3
Classifier: License :: OSI Approved :: MIT License
Classifier: Operating System :: OS Independent
Requires-Python: >=3.7
License-File: LICENSE
